setup.py
kst1/__init__.py
kst1/admin.py
kst1/apps.py
kst1/fields.py
kst1/forms.py
kst1/models.py
kst1/states.py
kst1/tests.py
kst1/views.py
kst1/migrations/__init__.py
pranav_indian_states_25/__init__.py
pranav_indian_states_25/asgi.py
pranav_indian_states_25/settings.py
pranav_indian_states_25/urls.py
pranav_indian_states_25/wsgi.py
pranav_indian_states_25.egg-info/PKG-INFO
pranav_indian_states_25.egg-info/SOURCES.txt
pranav_indian_states_25.egg-info/dependency_links.txt
pranav_indian_states_25.egg-info/requires.txt
pranav_indian_states_25.egg-info/top_level.txt